archerdfu/construct/__init__.py
archerdfu/construct/array_pointer.py
archerdfu/construct/checksum_stream.py
archerdfu/construct/detailed.py
archerdfu/construct/jsonify.py
archerdfu/construct/padded_cstring.py
archerdfu.construct-1.0.0.dist-info/LICENSE
archerdfu.construct-1.0.0.dist-info/METADATA
archerdfu.construct-1.0.0.dist-info/WHEEL
archerdfu.construct-1.0.0.dist-info/top_level.txt
archerdfu.construct-1.0.0.dist-info/RECORD
