Metadata-Version: 2.1
Name: archerdfu.construct
Version: 1.0.0
Summary: construct extension for archerdfu library
Author: o-murphy
License: GNU GENERAL PUBLIC LICENSE
Project-URL: Homepage, https://github.com/archerdfu/archerdfu.construct
Project-URL: Bug Reports, https://github.com/archerdfu/archerdfu.construct/issues
Project-URL: Source, https://github.com/archerdfu/archerdfu.construct
Keywords: ARCHER,archerdfu,pydfuutil,dfuutil
Classifier: Intended Audience :: Developers
Classifier: Natural Language :: English
Classifier: Programming Language :: Python
Classifier: Topic :: Software Development :: Libraries :: Python Modules
Classifier: Programming Language :: Python :: 3
Classifier: Programming Language :: Python :: 3 :: Only
Classifier: Programming Language :: Python :: 3.9
Classifier: Programming Language :: Python :: 3.10
Classifier: Programming Language :: Python :: 3.11
Classifier: Programming Language :: Python :: 3.12
Classifier: Programming Language :: Python :: Implementation :: CPython
Requires-Python: >=3.9
License-File: LICENSE
Requires-Dist: construct
